digitalhub_runtime_modelserve/__init__.py
digitalhub_runtime_modelserve/entities/__init__.py
digitalhub_runtime_modelserve/entities/_base/__init__.py
digitalhub_runtime_modelserve/entities/_base/runtime_entity/__init__.py
digitalhub_runtime_modelserve/entities/_base/runtime_entity/builder.py
digitalhub_runtime_modelserve/entities/_commons/__init__.py
digitalhub_runtime_modelserve/entities/_commons/enums.py
digitalhub_runtime_modelserve/entities/function/__init__.py
digitalhub_runtime_modelserve/entities/function/huggingfaceserve/__init__.py
digitalhub_runtime_modelserve/entities/function/huggingfaceserve/builder.py
digitalhub_runtime_modelserve/entities/function/huggingfaceserve/entity.py
digitalhub_runtime_modelserve/entities/function/huggingfaceserve/spec.py
digitalhub_runtime_modelserve/entities/function/huggingfaceserve/status.py
digitalhub_runtime_modelserve/entities/function/kubeaiserve/__init__.py
digitalhub_runtime_modelserve/entities/function/kubeaiserve/builder.py
digitalhub_runtime_modelserve/entities/function/kubeaiserve/entity.py
digitalhub_runtime_modelserve/entities/function/kubeaiserve/models.py
digitalhub_runtime_modelserve/entities/function/kubeaiserve/spec.py
digitalhub_runtime_modelserve/entities/function/kubeaiserve/status.py
digitalhub_runtime_modelserve/entities/function/kubeaiservespeechtotext/__init__.py
digitalhub_runtime_modelserve/entities/function/kubeaiservespeechtotext/builder.py
digitalhub_runtime_modelserve/entities/function/kubeaiservespeechtotext/entity.py
digitalhub_runtime_modelserve/entities/function/kubeaiservespeechtotext/spec.py
digitalhub_runtime_modelserve/entities/function/kubeaiservespeechtotext/status.py
digitalhub_runtime_modelserve/entities/function/kubeaiservetext/__init__.py
digitalhub_runtime_modelserve/entities/function/kubeaiservetext/builder.py
digitalhub_runtime_modelserve/entities/function/kubeaiservetext/entity.py
digitalhub_runtime_modelserve/entities/function/kubeaiservetext/enums.py
digitalhub_runtime_modelserve-0.14.7.dist-info/METADATA
digitalhub_runtime_modelserve-0.14.7.dist-info/WHEEL
digitalhub_runtime_modelserve-0.14.7.dist-info/licenses/AUTHORS
digitalhub_runtime_modelserve-0.14.7.dist-info/licenses/LICENSE
digitalhub_runtime_modelserve-0.14.7.dist-info/RECORD
