Metadata-Version: 2.4
Name: digitalhub-runtime-modelserve
Version: 0.14.7
Summary: ML Model serving runtime for DHCore
Project-URL: Homepage, https://github.com/scc-digitalhub/digitalhub-sdk-runtime-modelserve
Author-email: Fondazione Bruno Kessler <digitalhub@fbk.eu>, Matteo Martini <mmartini@fbk.eu>
License:                                  Apache License
License-File: AUTHORS
License-File: LICENSE
Keywords: kubernetes,ml,mlops
Classifier: License :: OSI Approved :: Apache Software License
Classifier: Programming Language :: Python :: 3.9
Classifier: Programming Language :: Python :: 3.10
Classifier: Programming Language :: Python :: 3.11
Classifier: Programming Language :: Python :: 3.12
Requires-Python: <3.13,>=3.9
Requires-Dist: digitalhub<0.15,>=0.14.0
Provides-Extra: dev
Requires-Dist: digitalhub[dev]<0.15,>=0.14.0; extra == 'dev'
